htg/__init__.py
htg/__main__.py
htg/defaults.py
htg/htg.py
htg/meta_example.py
htg/models.py
htg/classes/__init__.py
htg/classes/clean.py
htg/classes/config.py
htg/classes/index.py
htg/classes/json.py
htg/classes/resize.py
htg/classes/resize_simple.py
htg/classes/serve.py
htg/commands/__init__.py
htg/commands/album.py
htg/commands/config.py
htg/commands/groom.py
htg/commands/index.py
htg/commands/json.py
htg/commands/resize.py
htg/commands/util.py
htg/imaging/__init__.py
htg/imaging/average.py
htg/imaging/resize_im.py
htg/imaging/resize_pil.py
htg/imaging/resize_sips.py
htg/migrate/__init__.py
htg/migrate/in2ex.py
htg/utils/__init__.py
htg/utils/aliased_group.py
htg/utils/groom.py
htg/utils/validate.py
htg-0.7a2.dist-info/LICENSE
htg-0.7a2.dist-info/METADATA
htg-0.7a2.dist-info/WHEEL
htg-0.7a2.dist-info/entry_points.txt
htg-0.7a2.dist-info/top_level.txt
htg-0.7a2.dist-info/RECORD
